fairical/__init__.py
fairical/metrics.py
fairical/plot.py
fairical/scores.py
fairical/solutions.py
fairical/utils.py
fairical/scripts/__init__.py
fairical/scripts/cli.py
fairical/scripts/evaluate.py
fairical/scripts/plot.py
fairical/scripts/solve.py
fairical/scripts/utils.py
fairical-1.0.0.dist-info/METADATA
fairical-1.0.0.dist-info/WHEEL
fairical-1.0.0.dist-info/entry_points.txt
fairical-1.0.0.dist-info/RECORD
