Metadata-Version: 2.4
Name: fairical
Version: 1.0.0
Summary: Fairical is a Python library to assess adjustable demographically fair Machine Learning (ML) systems
Project-URL: documentation, https://fairical.readthedocs.io/en/v1.0.0/
Project-URL: homepage, https://pypi.org/project/fairical
Project-URL: repository, https://gitlab.idiap.ch/medai/software/fairical
Project-URL: changelog, https://gitlab.idiap.ch/medai/software/fairical/-/releases
Author-email: Gokhan Ozbulak <gokhan.ozbulak@idiap.ch>
License-Expression: GPL-3.0-or-later
Classifier: Development Status :: 4 - Beta
Classifier: Intended Audience :: Developers
Classifier: License :: OSI Approved :: GNU General Public License v3 (GPLv3)
Classifier: Natural Language :: English
Classifier: Programming Language :: Python :: 3
Classifier: Topic :: Software Development :: Libraries :: Python Modules
Requires-Python: >=3.11
Requires-Dist: click
Requires-Dist: compact-json
Requires-Dist: fairlearn
Requires-Dist: matplotlib
Requires-Dist: numpy
Requires-Dist: pydantic>=2
Requires-Dist: pymoo
Requires-Dist: scikit-learn
Requires-Dist: tabulate
Provides-Extra: doc
Requires-Dist: auto-intersphinx; extra == 'doc'
Requires-Dist: furo; extra == 'doc'
Requires-Dist: sphinx; extra == 'doc'
Requires-Dist: sphinx-autodoc-typehints; extra == 'doc'
Requires-Dist: sphinx-click; extra == 'doc'
Requires-Dist: sphinx-copybutton; extra == 'doc'
Requires-Dist: sphinx-inline-tabs; extra == 'doc'
Requires-Dist: sphinxcontrib-bibtex; extra == 'doc'
Provides-Extra: qa
Requires-Dist: pre-commit; extra == 'qa'
Provides-Extra: test
Requires-Dist: pytest; extra == 'test'
Requires-Dist: pytest-cov; extra == 'test'
